visiond/__init__.py
visiond-0.1.0.dist-info/WHEEL
visiond-0.1.0.dist-info/METADATA
visiond-0.1.0.dist-info/RECORD
