Metadata-Version: 2.1
Name: visiond
Version: 0.1.0
Summary: Algorithmic Trading Library
Author: Chris Bradley
Author-email: declarationcb@gmail.com
Requires-Python: >=3.7,<3.10
Classifier: Programming Language :: Python :: 3
Classifier: Programming Language :: Python :: 3.7
Classifier: Programming Language :: Python :: 3.8
Classifier: Programming Language :: Python :: 3.9
Requires-Dist: numpy (>=1.21.2,<2.0.0)
